setup.py
src/django_timelog.egg-info/PKG-INFO
src/django_timelog.egg-info/SOURCES.txt
src/django_timelog.egg-info/dependency_links.txt
src/django_timelog.egg-info/requires.txt
src/django_timelog.egg-info/top_level.txt
src/timelog/__init__.py
src/timelog/lib.py
src/timelog/middleware.py
src/timelog/management/__init__.py
src/timelog/management/commands/__init__.py
src/timelog/management/commands/analyze_timelog.py