Metadata-Version: 1.0
Name: django-timelog
Version: 0.1
Summary: Performance logging middlware and analysis tools for Django
Home-page: http://github.com/garethr/django-timelog/
Author: Gareth Rushgrove
Author-email: gareth@morethanseven.net
License: MIT License
Keywords: django
Platform: UNKNOWN
Classifier: Intended Audience :: Developers
Classifier: License :: OSI Approved :: MIT License
Classifier: Operating System :: OS Independent
Classifier: Programming Language :: Python
